{
    "id": 108882115,
    "name": "bludbath",
    "author": "dogeplaysdg",
    "creators": ["dogeplaysdg"],
    "verifier": "dogeplaysdg",
    "verification": "https://youtu.be/yYOallHVoGY",
    "percentToQualify": "67",
    "password": "Free To Copy",
    "records": [
        {
            "user": "Pixxi",
            "link": "https://www.youtube.com/watch?v=DV90bxQ7pgk",
            "percent": 100,
            "hz": 240
        },
        {
            "user": "TBA"
            "link": "https://youtu.be/b0gyQMJHQ78?si=HqRebnKF-GER9Lqq",
            "percent": 100,
            "hz": 60
    ]
}
